openbb_store/__init__.py
openbb_store/store.py
openbb_store/utils.py
openbb_store-0.1.2.dist-info/LICENSE
openbb_store-0.1.2.dist-info/METADATA
openbb_store-0.1.2.dist-info/WHEEL
openbb_store-0.1.2.dist-info/entry_points.txt
openbb_store-0.1.2.dist-info/RECORD
