Metadata-Version: 2.3
Name: openbb-store
Version: 0.1.2
Summary: An OBBject extension for object storage and data interchange.
Author: Danglewood
Author-email: 85772166+deeleeramone@users.noreply.github.com
Requires-Python: >=3.9.21,<3.13
Classifier: Programming Language :: Python :: 3
Classifier: Programming Language :: Python :: 3.10
Classifier: Programming Language :: Python :: 3.11
Classifier: Programming Language :: Python :: 3.12
Provides-Extra: all
Provides-Extra: charting
Provides-Extra: excel
Requires-Dist: dill (>=0.4.0,<0.5.0)
Requires-Dist: openbb-charting (>=2.3.2,<3.0.0) ; extra == "charting" or extra == "all"
Requires-Dist: openbb-core (>=1.4.4,<2.0.0)
Requires-Dist: openpyxl (>=3.1,<4.0) ; extra == "excel" or extra == "all"
Requires-Dist: random-user-agent (>=1,<2) ; extra == "excel" or extra == "all"
Requires-Dist: xlrd (>=2,<3) ; extra == "excel" or extra == "all"
